tipsy/__init__.py
tipsy/_version.py
tipsy/cached.py
tipsy/curry.py
tipsy/py.typed
tipsy/registry.py
tipsy/registry_helpers.py
tipsy/tipsy.py
tipsy/types.py
tipsy-0.7.1.dist-info/LICENSE
tipsy-0.7.1.dist-info/METADATA
tipsy-0.7.1.dist-info/WHEEL
tipsy-0.7.1.dist-info/top_level.txt
tipsy-0.7.1.dist-info/RECORD
