Metadata-Version: 2.1
Name: tipsy
Version: 0.7.1
Summary: tiny type narrowing library
Home-page: https://gitlab.com/martizih/tipsy.git
Author: Martin Zihlmann
Author-email: martizih@outlook.com
License: MIT
Classifier: Programming Language :: Python :: 3
Classifier: License :: Other/Proprietary License
Classifier: Operating System :: OS Independent
Requires-Python: >=3.10
License-File: LICENSE
